LICENSE
MANIFEST.in
README.rst
setup.py
django_ip_shield.egg-info/PKG-INFO
django_ip_shield.egg-info/SOURCES.txt
django_ip_shield.egg-info/dependency_links.txt
django_ip_shield.egg-info/top_level.txt
ipshield/__init__.py
ipshield/apps.py
ipshield/models.py
ipshield/views.py